kubiya/__init__.py
kubiya/action_store.py
kubiya/bundle.py
kubiya/helpers.py
kubiya/http.py
kubiya/loader.py
kubiya/secrets.py
kubiya/serve.py
kubiya/test.py
kubiya-0.1.3.dist-info/METADATA
kubiya-0.1.3.dist-info/WHEEL
kubiya-0.1.3.dist-info/RECORD
