Metadata-Version: 2.1
Name: kubiya
Version: 0.1.3
Summary: Kubiya is a DevOps virtual assistant that captures and converts organizational knowledge into self-service workflows for a delightful business, IT and Cloud operations experience.
Author: Kubiya
Author-email: info@kubiya.ai
Requires-Python: >3.7.2,<3.12
Classifier: Programming Language :: Python :: 3
Classifier: Programming Language :: Python :: 3.8
Classifier: Programming Language :: Python :: 3.9
Classifier: Programming Language :: Python :: 3.10
Classifier: Programming Language :: Python :: 3.11
Requires-Dist: fastapi (>=0.79.0,<0.80.0)
Requires-Dist: jsonschema (==4.17.3)
Requires-Dist: pydantic (==1.10.2)
Requires-Dist: uvicorn (>=0.18.2,<0.19.0)
